plaidml/keras/__init__.py
plaidml/keras/backend.py
plaidml_keras-0.6.4.dist-info/METADATA
plaidml_keras-0.6.4.dist-info/WHEEL
plaidml_keras-0.6.4.dist-info/top_level.txt
plaidml_keras-0.6.4.dist-info/RECORD
